peccipy/__init__.py
peccipy/main.py
peccipy-0.0.1.dist-info/METADATA
peccipy-0.0.1.dist-info/WHEEL
peccipy-0.0.1.dist-info/entry_points.txt
peccipy-0.0.1.dist-info/top_level.txt
peccipy-0.0.1.dist-info/RECORD
